odoo10_addon_product_supplierinfo_for_customer_picking-10.0.1.0.0.99.dev4-py3.8-nspkg.pth
odoo/addons/product_supplierinfo_for_customer_picking/README.rst
odoo/addons/product_supplierinfo_for_customer_picking/__init__.py
odoo/addons/product_supplierinfo_for_customer_picking/__manifest__.py
odoo/addons/product_supplierinfo_for_customer_picking/i18n/de.po
odoo/addons/product_supplierinfo_for_customer_picking/i18n/it.po
odoo/addons/product_supplierinfo_for_customer_picking/i18n/product_customer_code_picking.pot
odoo/addons/product_supplierinfo_for_customer_picking/i18n/product_supplierinfo_for_customer_picking.pot
odoo/addons/product_supplierinfo_for_customer_picking/models/__init__.py
odoo/addons/product_supplierinfo_for_customer_picking/models/stock_move.py
odoo/addons/product_supplierinfo_for_customer_picking/static/description/icon.png
odoo/addons/product_supplierinfo_for_customer_picking/tests/__init__.py
odoo/addons/product_supplierinfo_for_customer_picking/tests/test_product_supplierinfo_for_customer_picking.py
odoo/addons/product_supplierinfo_for_customer_picking/views/stock_picking_view.xml
odoo10_addon_product_supplierinfo_for_customer_picking-10.0.1.0.0.99.dev4.dist-info/METADATA
odoo10_addon_product_supplierinfo_for_customer_picking-10.0.1.0.0.99.dev4.dist-info/WHEEL
odoo10_addon_product_supplierinfo_for_customer_picking-10.0.1.0.0.99.dev4.dist-info/namespace_packages.txt
odoo10_addon_product_supplierinfo_for_customer_picking-10.0.1.0.0.99.dev4.dist-info/top_level.txt
odoo10_addon_product_supplierinfo_for_customer_picking-10.0.1.0.0.99.dev4.dist-info/RECORD
