Metadata-Version: 2.1
Name: odoo10-addon-product-supplierinfo-for-customer-picking
Version: 10.0.1.0.0.99.dev4
Summary: This module makes the product customer code visible in the stock moves of a picking.
Home-page: https://github.com/OCA/stock-logistics-workflow
Author: Agile Business Group, Odoo Community Association (OCA)
Author-email: support@odoo-community.org
License: AGPL-3
Platform: UNKNOWN
Classifier: Programming Language :: Python
Classifier: Framework :: Odoo
Classifier: Framework :: Odoo :: 10.0
Classifier: License :: OSI Approved :: GNU Affero General Public License v3
Requires-Python: ~=2.7
Requires-Dist: odoo10-addon-product-supplierinfo-for-customer
Requires-Dist: odoo (<10.1dev,>=10.0)
